{"frameRate":48,"armature":[{"frameRate":48,"skin":[{"name":"","slot":[{"display":[{"type":"image","transform":{"y":-1.9701,"skX":92.7702,"skY":92.7702,"x":3.249},"name":"body2_1","path":"body2_1"}],"name":"body2_1"},{"display":[{"type":"image","transform":{"y":1.4925,"skX":-90,"skY":-90,"x":7.5385},"name":"leg2_1_1","path":"leg2_1_1"}],"name":"leg2_1_1"},{"display":[{"type":"image","transform":{"y":1.4443,"skX":-52.864,"skY":-52.864,"x":5.6872},"name":"arm2_2_2","path":"arm2_2_2"}],"name":"arm2_2_2"},{"display":[{"type":"image","transform":{"y":-1.2406,"skX":-88.632,"skY":-88.632,"x":8.0234},"name":"leg2_2_1","path":"leg2_2_1"}],"name":"leg2_2_1"},{"display":[{"type":"image","transform":{"y":-2.5641,"skX":91.625,"skY":91.625,"x":21.1834},"name":"head2","path":"head2"}],"name":"head2"},{"display":[{"type":"image","transform":{"y":0.3828,"skX":-108.5183,"skY":-108.5183,"x":6.1261},"name":"arm2_1_1","path":"arm2_1_1"}],"name":"arm2_1_1"},{"display":[{"type":"image","transform":{"y":-1.008,"skX":-111.9087,"skY":-111.9087,"x":6.2193},"name":"arm2_1_2","path":"arm2_1_2"}],"name":"arm2_1_2"},{"display":[{"type":"image","transform":{"y":-1.6423,"skX":-90,"skY":-90,"x":6.0342},"name":"leg2_1_2","path":"leg2_1_2"}],"name":"leg2_1_2"},{"display":[{"type":"image","transform":{"y":-0.1225,"skX":-58.7961,"skY":-58.7961,"x":5.3409},"name":"arm2_2_1","path":"arm2_2_1"}],"name":"arm2_2_1"},{"display":[{"type":"image","transform":{"y":-0.6721,"skX":-90,"skY":-90,"x":3.8124},"name":"leg2_2_2","path":"leg2_2_2"}],"name":"leg2_2_2"},{"display":[{"type":"image","transform":{"y":-1.8435,"x":2.0882},"name":"body2","path":"body2"}],"name":"body2"},{"display":[{"type":"image","transform":{"y":-0.5166,"x":0.7676},"name":"yinying","path":"yinying"}],"name":"yinying"}]}],"bone":[{"transform":{},"name":"root"},{"transform":{"y":-5.25,"x":2.6403},"name":"yinying","parent":"root"},{"length":16,"parent":"root","transform":{"y":-36.0211,"skX":88.632,"skY":88.632,"x":-1.6136},"name":"leg2_1"},{"length":18,"parent":"root","transform":{"y":-38.6385,"skX":-92.7702,"skY":-92.7702,"x":3.9364},"name":"body"},{"length":15,"parent":"root","transform":{"y":-35.6385,"skX":90,"skY":90,"x":8.4364},"name":"leg1_1"},{"transform":{"y":-6.0385,"x":-1.1136},"name":"bone_ikTarget1","parent":"root"},{"transform":{"y":-6.1859,"x":8.5208},"name":"bone_ikTarget","parent":"root"},{"length":14,"parent":"leg1_1","transform":{"y":0.1459,"skX":-0.9423,"skY":-0.9423,"x":15.4545},"name":"leg1_2"},{"length":10,"parent":"body","transform":{"y":-4.8461,"skX":-162.8688,"skY":-162.8688,"x":16.1088},"name":"arm2_1"},{"length":49,"parent":"body","transform":{"y":1.7649,"skX":1.1452,"skY":1.1452,"x":21.9904},"name":"hair1"},{"transform":{"y":6.051,"skX":92.7702,"skY":92.7702,"x":10.2195},"name":"body2","parent":"body"},{"length":14,"parent":"leg2_1","transform":{"y":-0.1059,"skX":1.368,"skY":1.368,"x":16.5072},"name":"leg2_2"},{"length":10,"parent":"body","transform":{"y":6.9529,"skX":157.8482,"skY":157.8482,"x":14.6222},"name":"arm1_1"},{"length":9,"parent":"arm2_1","transform":{"y":0.0874,"skX":3.3904,"skY":3.3904,"x":11.1554},"name":"arm2_2"},{"length":12,"parent":"arm1_1","transform":{"y":0.2331,"skX":-5.9321,"skY":-5.9321,"x":10.6149},"name":"arm1_2"}],"ik":[{"target":"bone_ikTarget","bone":"leg1_2","name":"bone_ik"},{"target":"bone_ikTarget1","bone":"leg2_2","name":"bone_ik1"}],"defaultActions":[{"gotoAndPlay":"Breath"}],"aabb":{"x":-25.527404865332915,"y":-109.29064803807552,"width":54,"height":113.02405564351864},"type":"Armature","name":"Armature","animation":[{"ffd":[],"duration":20,"bone":[{"frame":[{"duration":20,"transform":{}}],"name":"root"},{"frame":[{"duration":10,"transform":{"scY":0.95,"scX":0.95},"tweenEasing":0},{"duration":10,"transform":{},"tweenEasing":0},{"duration":0,"transform":{"scY":0.95,"scX":0.95}}],"name":"yinying"},{"frame":[{"duration":10,"transform":{},"tweenEasing":0},{"duration":10,"transform":{"y":-0.52},"tweenEasing":0},{"duration":0,"transform":{}}],"name":"body"},{"frame":[{"duration":20,"transform":{}}],"name":"hair1"},{"frame":[{"duration":10,"transform":{},"tweenEasing":0},{"duration":10,"transform":{"skX":5.0985,"skY":5.0985},"tweenEasing":0},{"duration":0,"transform":{}}],"name":"arm1_1"},{"frame":[{"duration":10,"transform":{},"tweenEasing":0},{"duration":10,"transform":{"skX":-4.0679,"skY":-4.0679},"tweenEasing":0},{"duration":0,"transform":{}}],"name":"arm1_2"},{"frame":[{"duration":10,"transform":{},"tweenEasing":0},{"duration":10,"transform":{"skX":-4.2186,"skY":-4.2186},"tweenEasing":0},{"duration":0,"transform":{}}],"name":"arm2_1"},{"frame":[{"duration":10,"transform":{},"tweenEasing":0},{"duration":10,"transform":{"skX":3.4096,"skY":3.4096},"tweenEasing":0},{"duration":0,"transform":{}}],"name":"arm2_2"},{"frame":[{"duration":20,"transform":{}}],"name":"body2"},{"frame":[{"duration":20,"transform":{}}],"name":"leg1_1"},{"frame":[{"duration":20,"transform":{}}],"name":"leg1_2"},{"frame":[{"duration":20,"transform":{}}],"name":"leg2_1"},{"frame":[{"duration":20,"transform":{}}],"name":"leg2_2"},{"frame":[{"duration":20,"transform":{}}],"name":"bone_ikTarget"},{"frame":[{"duration":20,"transform":{}}],"name":"bone_ikTarget1"}],"playTimes":0,"frame":[],"slot":[],"name":"Breath","ik":[]},{"ffd":[],"duration":40,"bone":[{"frame":[{"duration":40,"transform":{}}],"name":"root"},{"frame":[{"duration":10,"transform":{"scY":0.95,"scX":0.95},"tweenEasing":0},{"duration":10,"transform":{},"tweenEasing":0},{"duration":10,"transform":{"scY":0.95,"scX":0.95},"tweenEasing":0},{"duration":10,"transform":{},"tweenEasing":0},{"duration":0,"transform":{"scY":0.95,"scX":0.95}}],"name":"yinying"},{"frame":[{"duration":10,"transform":{},"tweenEasing":0},{"duration":10,"transform":{"y":-0.99},"tweenEasing":0},{"duration":10,"transform":{},"tweenEasing":0},{"duration":10,"transform":{"y":-0.99},"tweenEasing":0},{"duration":0,"transform":{}}],"name":"body"},{"frame":[{"duration":40,"transform":{}}],"name":"hair1"},{"frame":[{"duration":40,"transform":{}}],"name":"arm1_1"},{"frame":[{"duration":40,"transform":{"y":-0.3575,"skX":-62.0838,"skY":-62.0838,"x":-0.5902}}],"name":"arm1_2"},{"frame":[{"duration":40,"transform":{}}],"name":"arm2_1"},{"frame":[{"duration":40,"transform":{"skX":-112.4526,"skY":-112.4526}}],"name":"arm2_2"},{"frame":[{"duration":40,"transform":{}}],"name":"body2"},{"frame":[{"duration":10,"transform":{},"tweenEasing":0},{"duration":10,"transform":{"skX":-30.6271,"skY":-30.6271},"tweenEasing":0},{"duration":10,"transform":{},"tweenEasing":0},{"duration":10,"transform":{"skX":26.2837,"skY":26.2837},"tweenEasing":0},{"duration":0,"transform":{}}],"name":"leg1_1"},{"frame":[{"duration":40,"transform":{}}],"name":"leg1_2"},{"frame":[{"duration":10,"transform":{},"tweenEasing":0},{"duration":10,"transform":{"skX":16.7909,"skY":16.7909},"tweenEasing":0},{"duration":10,"transform":{},"tweenEasing":0},{"duration":10,"transform":{"skX":-40.7249,"skY":-40.7249},"tweenEasing":0},{"duration":0,"transform":{}}],"name":"leg2_1"},{"frame":[{"duration":40,"transform":{}}],"name":"leg2_2"},{"frame":[{"duration":4,"transform":{},"tweenEasing":0},{"duration":6,"transform":{"y":0.2677,"x":5.4382},"tweenEasing":0},{"duration":6,"transform":{"y":-2.5377,"x":16.6751},"tweenEasing":0},{"duration":4,"transform":{"x":8.5494},"tweenEasing":0},{"duration":4,"transform":{},"tweenEasing":0},{"duration":6,"transform":{"y":0.9231,"x":-8.1776},"tweenEasing":0},{"duration":6,"transform":{"y":1.5385,"x":-17.3871},"tweenEasing":0},{"duration":4,"transform":{"y":0.9231,"x":-14.3951},"tweenEasing":0},{"duration":0,"transform":{}}],"name":"bone_ikTarget"},{"frame":[{"duration":4,"transform":{},"tweenEasing":0},{"duration":6,"transform":{"x":-3.1092},"tweenEasing":0},{"duration":6,"transform":{"y":0.5526,"x":-17.2024},"tweenEasing":0},{"duration":4,"transform":{"y":-1.2895,"x":-10.3961},"tweenEasing":0},{"duration":4,"transform":{},"tweenEasing":0},{"duration":6,"transform":{"x":5.7094},"tweenEasing":0},{"duration":6,"transform":{"y":1.6106,"x":28.1853},"tweenEasing":0},{"duration":4,"transform":{"y":0.6442,"x":10.2762},"tweenEasing":0},{"duration":0,"transform":{}}],"name":"bone_ikTarget1"}],"playTimes":0,"frame":[],"slot":[],"zOrder":{"frame":[{"duration":40,"zOrder":[],"tweenEasing":null}]},"name":"walk2","ik":[]},{"ffd":[],"duration":40,"bone":[{"frame":[{"duration":40,"transform":{}}],"name":"root"},{"frame":[{"duration":10,"transform":{"scY":0.95,"scX":0.95},"tweenEasing":0},{"duration":10,"transform":{},"tweenEasing":0},{"duration":10,"transform":{"scY":0.95,"scX":0.95},"tweenEasing":0},{"duration":10,"transform":{},"tweenEasing":0},{"duration":0,"transform":{"scY":0.95,"scX":0.95}}],"name":"yinying"},{"frame":[{"duration":10,"transform":{},"tweenEasing":0},{"duration":10,"transform":{"y":-0.99},"tweenEasing":0},{"duration":10,"transform":{},"tweenEasing":0},{"duration":10,"transform":{"y":-0.99},"tweenEasing":0},{"duration":0,"transform":{}}],"name":"body"},{"frame":[{"duration":40,"transform":{}}],"name":"hair1"},{"frame":[{"duration":10,"transform":{},"tweenEasing":0},{"duration":20,"transform":{"skX":47.7361,"skY":47.7361},"tweenEasing":0},{"duration":10,"transform":{"skX":-34.0736,"skY":-34.0736},"tweenEasing":0},{"duration":0,"transform":{}}],"name":"arm1_1"},{"frame":[{"duration":40,"transform":{}}],"name":"arm1_2"},{"frame":[{"duration":10,"transform":{},"tweenEasing":0},{"duration":20,"transform":{"skX":-56.0558,"skY":-56.0558},"tweenEasing":0},{"duration":10,"transform":{"skX":26.2742,"skY":26.2742},"tweenEasing":0},{"duration":0,"transform":{}}],"name":"arm2_1"},{"frame":[{"duration":40,"transform":{}}],"name":"arm2_2"},{"frame":[{"duration":40,"transform":{}}],"name":"body2"},{"frame":[{"duration":10,"transform":{},"tweenEasing":0},{"duration":10,"transform":{"skX":-30.6271,"skY":-30.6271},"tweenEasing":0},{"duration":10,"transform":{},"tweenEasing":0},{"duration":10,"transform":{"skX":26.2837,"skY":26.2837},"tweenEasing":0},{"duration":0,"transform":{}}],"name":"leg1_1"},{"frame":[{"duration":40,"transform":{}}],"name":"leg1_2"},{"frame":[{"duration":10,"transform":{},"tweenEasing":0},{"duration":10,"transform":{"skX":16.7909,"skY":16.7909},"tweenEasing":0},{"duration":10,"transform":{},"tweenEasing":0},{"duration":10,"transform":{"skX":-40.7249,"skY":-40.7249},"tweenEasing":0},{"duration":0,"transform":{}}],"name":"leg2_1"},{"frame":[{"duration":40,"transform":{}}],"name":"leg2_2"},{"frame":[{"duration":4,"transform":{},"tweenEasing":0},{"duration":6,"transform":{"y":0.2677,"x":5.4382},"tweenEasing":0},{"duration":6,"transform":{"y":-2.5377,"x":16.6751},"tweenEasing":0},{"duration":4,"transform":{"x":8.5494},"tweenEasing":0},{"duration":4,"transform":{},"tweenEasing":0},{"duration":6,"transform":{"y":0.9231,"x":-8.1776},"tweenEasing":0},{"duration":6,"transform":{"y":1.5385,"x":-17.3871},"tweenEasing":0},{"duration":4,"transform":{"y":0.9231,"x":-14.3951},"tweenEasing":0},{"duration":0,"transform":{}}],"name":"bone_ikTarget"},{"frame":[{"duration":4,"transform":{},"tweenEasing":0},{"duration":6,"transform":{"x":-3.1092},"tweenEasing":0},{"duration":6,"transform":{"y":0.5526,"x":-17.2024},"tweenEasing":0},{"duration":4,"transform":{"y":-1.2895,"x":-10.3961},"tweenEasing":0},{"duration":4,"transform":{},"tweenEasing":0},{"duration":6,"transform":{"x":5.7094},"tweenEasing":0},{"duration":6,"transform":{"y":1.6106,"x":28.1853},"tweenEasing":0},{"duration":4,"transform":{"y":0.6442,"x":10.2762},"tweenEasing":0},{"duration":0,"transform":{}}],"name":"bone_ikTarget1"}],"playTimes":0,"frame":[],"slot":[],"name":"walk1","ik":[]}],"slot":[{"color":{"aM":75},"name":"yinying","parent":"yinying"},{"z":1,"color":{},"name":"body2","parent":"body2"},{"z":2,"color":{},"name":"leg2_2_1","parent":"leg2_1"},{"z":3,"color":{},"name":"leg2_2_2","parent":"leg2_2"},{"z":4,"color":{},"name":"leg2_1_1","parent":"leg1_1"},{"z":5,"color":{},"name":"leg2_1_2","parent":"leg1_2"},{"z":6,"color":{},"name":"arm2_1_1","parent":"arm2_1"},{"z":7,"color":{},"name":"arm2_1_2","parent":"arm2_2"},{"z":8,"color":{},"name":"body2_1","parent":"body"},{"z":9,"color":{},"name":"arm2_2_1","parent":"arm1_1"},{"z":10,"color":{},"name":"arm2_2_2","parent":"arm1_2"},{"z":11,"color":{},"name":"head2","parent":"hair1"}]}],"version":"5.0","name":"animation_role2_2","isGlobal":0}